[
  {
    "id": 673,
    "title": "探偵オペラ ミルキィホームズ アルセーヌ 華麗なる欲望",
    "title_short1": "ミルキィホームズ",
    "title_short2": "",
    "title_short3": "",
    "title_en": "",
    "public_url": "https://sp.bushiroad.com/special_tv/",
    "twitter_account": "milkyholmes",
    "twitter_hash_tag": "milkyholmes",
    "cours_id": 0,
    "created_at": "2018-01-07T20:29:38Z",
    "updated_at": "2018-01-07T20:29:38Z",
    "sex": 0,
    "sequel": 5,
    "city_code": 0,
    "city_name": "",
    "product_companies": "",
    "ogp_image_url": "not_found",
    "ogp_description": "not_found"
  },
  {
    "id": 674,
    "title": "アイドリッシュセブン",
    "title_short1": "アイドリッシュセブン",
    "title_short2": "",
    "title_short3": "",
    "title_en": "",
    "public_url": "http://idolish7.com/aninana/",
    "twitter_account": "iD7Mng_Ogami",
    "twitter_hash_tag": "アイナナ",
    "cours_id": 0,
    "created_at": "2018-01-07T20:29:38Z",
    "updated_at": "2018-01-07T20:29:38Z",
    "sex": 1,
    "sequel": 0,
    "city_code": 0,
    "city_name": "",
    "product_companies": "",
    "ogp_image_url": "not_found",
    "ogp_description": "not_found"
  },
  {
    "id": 675,
    "title": "宇宙よりも遠い場所",
    "title_short1": "宇宙よりも遠い場所",
    "title_short2": "",
    "title_short3": "",
    "title_en": "",
    "public_url": "http://yorimoi.com/",
    "twitter_account": "yorimoi",
    "twitter_hash_tag": "よりもい",
    "cours_id": 0,
    "created_at": "2018-01-07T20:29:38Z",
    "updated_at": "2018-01-07T20:29:38Z",
    "sex": 0,
    "sequel": 0,
    "city_code": 0,
    "city_name": "",
    "product_companies": "",
    "ogp_image_url": "not_found",
    "ogp_description": "not_found"
  },
  {
    "id": 676,
    "title": "ダメプリ ANIME CARAVAN",
    "title_short1": "ダメプリ",
    "title_short2": "",
    "title_short3": "",
    "title_en": "",
    "public_url": "https://damepri-anime.jp/",
    "twitter_account": "damepri_anime",
    "twitter_hash_tag": "ダメプリ",
    "cours_id": 0,
    "created_at": "2018-01-07T20:29:38Z",
    "updated_at": "2018-01-07T20:29:38Z",
    "sex": 1,
    "sequel": 0,
    "city_code": 0,
    "city_name": "",
    "product_companies": "",
    "ogp_image_url": "not_found",
    "ogp_description": "not_found"
  },
  {
    "id": 677,
    "title": "ラーメン大好き小泉さん",
    "title_short1": "ラーメン大好き小泉さん",
    "title_short2": "小泉さん",
    "title_short3": "",
    "title_en": "",
    "public_url": "http://ramen-koizumi.com/",
    "twitter_account": "ramen_koizumi",
    "twitter_hash_tag": "ラーメン大好き小泉さん",
    "cours_id": 0,
    "created_at": "2018-01-07T20:29:38Z",
    "updated_at": "2018-01-07T20:29:38Z",
    "sex": 0,
    "sequel": 0,
    "city_code": 0,
    "city_name": "",
    "product_companies": "",
    "ogp_image_url": "not_found",
    "ogp_description": "not_found"
  },
  {
    "id": 678,
    "title": "ゆるキャン△",
    "title_short1": "ゆるキャン△",
    "title_short2": "",
    "title_short3": "",
    "title_en": "",
    "public_url": "http://yurucamp.jp/",
    "twitter_account": "yurucamp_anime",
    "twitter_hash_tag": "ゆるキャン",
    "cours_id": 0,
    "created_at": "2018-01-07T20:29:38Z",
    "updated_at": "2018-01-07T20:29:38Z",
    "sex": 0,
    "sequel": 0,
    "city_code": 0,
    "city_name": "",
    "product_companies": "",
    "ogp_image_url": "not_found",
    "ogp_description": "not_found"
  },
  {
    "id": 679,
    "title": "刀使ノ巫女",
    "title_short1": "刀使ノ巫女",
    "title_short2": "",
    "title_short3": "",
    "title_en": "",
    "public_url": "http://tojinomiko.jp/",
    "twitter_account": "tojinomiko",
    "twitter_hash_tag": "tojinomiko",
    "cours_id": 0,
    "created_at": "2018-01-07T20:29:38Z",
    "updated_at": "2018-01-07T20:29:38Z",
    "sex": 0,
    "sequel": 0,
    "city_code": 0,
    "city_name": "",
    "product_companies": "",
    "ogp_image_url": "not_found",
    "ogp_description": "not_found"
  },
  {
    "id": 680,
    "title": "働くお兄さん！",
    "title_short1": "働くお兄さん",
    "title_short2": "",
    "title_short3": "",
    "title_en": "",
    "public_url": "http://www.hataoni.jp/",
    "twitter_account": "hataoni",
    "twitter_hash_tag": "はたおに",
    "cours_id": 0,
    "created_at": "2018-01-07T20:29:38Z",
    "updated_at": "2018-01-07T20:29:38Z",
    "sex": 0,
    "sequel": 0,
    "city_code": 0,
    "city_name": "",
    "product_companies": "",
    "ogp_image_url": "not_found",
    "ogp_description": "not_found"
  },
  {
    "id": 681,
    "title": "伊藤潤二「コレクション」",
    "title_short1": "伊藤潤二",
    "title_short2": "",
    "title_short3": "",
    "title_en": "",
    "public_url": "http://itojunji-anime.com/",
    "twitter_account": "itojunji_anime",
    "twitter_hash_tag": "伊藤潤二",
    "cours_id": 0,
    "created_at": "2018-01-07T20:29:38Z",
    "updated_at": "2018-01-07T20:29:38Z",
    "sex": 0,
    "sequel": 0,
    "city_code": 0,
    "city_name": "",
    "product_companies": "",
    "ogp_image_url": "not_found",
    "ogp_description": "not_found"
  },
  {
    "id": 682,
    "title": "グランクレスト戦記",
    "title_short1": "グランクレスト",
    "title_short2": "",
    "title_short3": "",
    "title_en": "",
    "public_url": "http://grancrest-anime.jp/",
    "twitter_account": "grancrest_anime",
    "twitter_hash_tag": "グラクレ",
    "cours_id": 0,
    "created_at": "2018-01-07T20:29:38Z",
    "updated_at": "2018-01-07T20:29:38Z",
    "sex": 0,
    "sequel": 0,
    "city_code": 0,
    "city_name": "",
    "product_companies": "",
    "ogp_image_url": "not_found",
    "ogp_description": "not_found"
  },
  {
    "id": 683,
    "title": "DEVILMAN crybaby",
    "title_short1": "DEVILMAN crybaby",
    "title_short2": "",
    "title_short3": "",
    "title_en": "",
    "public_url": "http://devilman-crybaby.com/",
    "twitter_account": "DevilmanCryBaby",
    "twitter_hash_tag": "devilman",
    "cours_id": 0,
    "created_at": "2018-01-07T20:29:38Z",
    "updated_at": "2018-01-07T20:29:38Z",
    "sex": 0,
    "sequel": 0,
    "city_code": 0,
    "city_name": "",
    "product_companies": "",
    "ogp_image_url": "not_found",
    "ogp_description": "not_found"
  },
  {
    "id": 684,
    "title": "七つの大罪 戒めの復活",
    "title_short1": "七つの大罪",
    "title_short2": "",
    "title_short3": "",
    "title_en": "",
    "public_url": "http://www.7-taizai.net/",
    "twitter_account": "7_taizai",
    "twitter_hash_tag": "七つの大罪",
    "cours_id": 0,
    "created_at": "2018-01-07T20:29:38Z",
    "updated_at": "2018-01-07T20:29:38Z",
    "sex": 0,
    "sequel": 2,
    "city_code": 0,
    "city_name": "",
    "product_companies": "",
    "ogp_image_url": "not_found",
    "ogp_description": "not_found"
  },
  {
    "id": 686,
    "title": "サンリオ男子",
    "title_short1": "サンリオ男子",
    "title_short2": "",
    "title_short3": "",
    "title_en": "",
    "public_url": "http://sdan-anime.com/",
    "twitter_account": "Sdan_Anime",
    "twitter_hash_tag": "SdanA",
    "cours_id": 0,
    "created_at": "2018-01-07T20:29:38Z",
    "updated_at": "2018-01-07T20:29:38Z",
    "sex": 1,
    "sequel": 0,
    "city_code": 0,
    "city_name": "",
    "product_companies": "",
    "ogp_image_url": "not_found",
    "ogp_description": "not_found"
  },
  {
    "id": 687,
    "title": "citrus",
    "title_short1": "citrus",
    "title_short2": "",
    "title_short3": "",
    "title_en": "",
    "public_url": "http://citrus-anime.com/",
    "twitter_account": "citrus_anime",
    "twitter_hash_tag": "citrus",
    "cours_id": 0,
    "created_at": "2018-01-07T20:29:38Z",
    "updated_at": "2018-01-07T20:29:38Z",
    "sex": 0,
    "sequel": 0,
    "city_code": 0,
    "city_name": "",
    "product_companies": "",
    "ogp_image_url": "not_found",
    "ogp_description": "not_found"
  },
  {
    "id": 688,
    "title": "ダーリン・イン・ザ・フランキス",
    "title_short1": "ダーリン・イン・ザ・フランキス",
    "title_short2": "",
    "title_short3": "",
    "title_en": "",
    "public_url": "http://darli-fra.jp/",
    "twitter_account": "DARLI_FRA",
    "twitter_hash_tag": "ダリフラ",
    "cours_id": 0,
    "created_at": "2018-01-07T20:29:38Z",
    "updated_at": "2018-01-07T20:29:38Z",
    "sex": 0,
    "sequel": 0,
    "city_code": 0,
    "city_name": "",
    "product_companies": "",
    "ogp_image_url": "not_found",
    "ogp_description": "not_found"
  },
  {
    "id": 689,
    "title": "刻刻",
    "title_short1": "刻刻",
    "title_short2": "",
    "title_short3": "",
    "title_en": "",
    "public_url": "http://kokkoku-anime.com/",
    "twitter_account": "geno_studio",
    "twitter_hash_tag": "kokkoku_anime",
    "cours_id": 0,
    "created_at": "2018-01-07T20:29:38Z",
    "updated_at": "2018-01-07T20:29:38Z",
    "sex": 0,
    "sequel": 0,
    "city_code": 0,
    "city_name": "",
    "product_companies": "",
    "ogp_image_url": "not_found",
    "ogp_description": "not_found"
  },
  {
    "id": 690,
    "title": "スロウスタート",
    "title_short1": "スロウスタート",
    "title_short2": "",
    "title_short3": "",
    "title_en": "",
    "public_url": "http://slow-start.com/",
    "twitter_account": "slosta_anime",
    "twitter_hash_tag": "スロウスタート",
    "cours_id": 0,
    "created_at": "2018-01-07T20:29:38Z",
    "updated_at": "2018-01-07T20:29:38Z",
    "sex": 0,
    "sequel": 0,
    "city_code": 0,
    "city_name": "",
    "product_companies": "",
    "ogp_image_url": "not_found",
    "ogp_description": "not_found"
  },
  {
    "id": 691,
    "title": "ポプテピピック",
    "title_short1": "ポプテピピック",
    "title_short2": "",
    "title_short3": "",
    "title_en": "",
    "public_url": "http://hoshiiro.jp/",
    "twitter_account": "hoshiiro_anime",
    "twitter_hash_tag": "ポプテピピック",
    "cours_id": 0,
    "created_at": "2018-01-07T20:29:38Z",
    "updated_at": "2018-01-07T20:29:38Z",
    "sex": 0,
    "sequel": 0,
    "city_code": 0,
    "city_name": "",
    "product_companies": "",
    "ogp_image_url": "not_found",
    "ogp_description": "not_found"
  },
  {
    "id": 692,
    "title": "カードキャプターさくら クリアカード編",
    "title_short1": "カードキャプターさくら",
    "title_short2": "ccさくら",
    "title_short3": "",
    "title_en": "",
    "public_url": "http://www.nhk.or.jp/anime/ccsakura/",
    "twitter_account": "ccsakura_info",
    "twitter_hash_tag": "ccsakura",
    "cours_id": 0,
    "created_at": "2018-01-07T20:29:38Z",
    "updated_at": "2018-01-07T20:29:38Z",
    "sex": 0,
    "sequel": 2,
    "city_code": 0,
    "city_name": "",
    "product_companies": "",
    "ogp_image_url": "not_found",
    "ogp_description": "not_found"
  },
  {
    "id": 693,
    "title": "三ツ星カラーズ",
    "title_short1": "三ツ星カラーズ",
    "title_short2": "",
    "title_short3": "",
    "title_en": "",
    "public_url": "http://mitsuboshi-anime.com/",
    "twitter_account": "3boshi_anime",
    "twitter_hash_tag": "三ツ星カラーズ",
    "cours_id": 0,
    "created_at": "2018-01-07T20:29:38Z",
    "updated_at": "2018-01-07T20:29:38Z",
    "sex": 0,
    "sequel": 0,
    "city_code": 0,
    "city_name": "",
    "product_companies": "",
    "ogp_image_url": "not_found",
    "ogp_description": "not_found"
  },
  {
    "id": 694,
    "title": "学園ベビーシッターズ",
    "title_short1": "学園ベビーシッターズ",
    "title_short2": "",
    "title_short3": "",
    "title_en": "",
    "public_url": "http://gakubaby-anime.com/",
    "twitter_account": "gakubaby_anime",
    "twitter_hash_tag": "学ベビ",
    "cours_id": 0,
    "created_at": "2018-01-07T20:29:38Z",
    "updated_at": "2018-01-07T20:29:38Z",
    "sex": 1,
    "sequel": 0,
    "city_code": 0,
    "city_name": "",
    "product_companies": "",
    "ogp_image_url": "not_found",
    "ogp_description": "not_found"
  },
  {
    "id": 695,
    "title": "続『刀剣乱舞-花丸-』",
    "title_short1": "刀剣乱舞",
    "title_short2": "",
    "title_short3": "",
    "title_en": "",
    "public_url": "http://touken-hanamaru.jp/",
    "twitter_account": "touken_hanamaru",
    "twitter_hash_tag": "touken_hanamaru",
    "cours_id": 0,
    "created_at": "2018-01-07T20:29:38Z",
    "updated_at": "2018-01-07T20:29:38Z",
    "sex": 1,
    "sequel": 2,
    "city_code": 0,
    "city_name": "",
    "product_companies": "",
    "ogp_image_url": "not_found",
    "ogp_description": "not_found"
  },
  {
    "id": 696,
    "title": "25歳の女子高生",
    "title_short1": "25歳の女子高生",
    "title_short2": "",
    "title_short3": "",
    "title_en": "",
    "public_url": "http://nigojo.cf-anime.com/",
    "twitter_account": "ComicFestaAnime",
    "twitter_hash_tag": "にごじょ",
    "cours_id": 0,
    "created_at": "2018-01-07T20:29:38Z",
    "updated_at": "2018-01-07T20:29:38Z",
    "sex": 1,
    "sequel": 0,
    "city_code": 0,
    "city_name": "",
    "product_companies": "",
    "ogp_image_url": "not_found",
    "ogp_description": "not_found"
  },
  {
    "id": 697,
    "title": "りゅうおうのおしごと！",
    "title_short1": "りゅうおうのおしごと",
    "title_short2": "",
    "title_short3": "",
    "title_en": "",
    "public_url": "http://www.ryuoh-anime.com/",
    "twitter_account": "Ryuoshi_PR",
    "twitter_hash_tag": "りゅうおうのおしごと",
    "cours_id": 0,
    "created_at": "2018-01-07T20:29:38Z",
    "updated_at": "2018-01-07T20:29:38Z",
    "sex": 0,
    "sequel": 0,
    "city_code": 0,
    "city_name": "",
    "product_companies": "",
    "ogp_image_url": "not_found",
    "ogp_description": "not_found"
  },
  {
    "id": 698,
    "title": "からかい上手の高木さん",
    "title_short1": "からかい上手の高木さん",
    "title_short2": "",
    "title_short3": "",
    "title_en": "",
    "public_url": "http://takagi3.me",
    "twitter_account": "takagi3_anime",
    "twitter_hash_tag": "高木さんめ",
    "cours_id": 0,
    "created_at": "2018-01-07T20:29:38Z",
    "updated_at": "2018-01-07T20:29:38Z",
    "sex": 0,
    "sequel": 0,
    "city_code": 0,
    "city_name": "",
    "product_companies": "",
    "ogp_image_url": "not_found",
    "ogp_description": "not_found"
  },
  {
    "id": 699,
    "title": "バジリスク～桜花忍法帖～",
    "title_short1": "バジリスク",
    "title_short2": "",
    "title_short3": "",
    "title_en": "",
    "public_url": "http://basilisk-ouka.jp/",
    "twitter_account": "basiliskouka",
    "twitter_hash_tag": "バジリスク",
    "cours_id": 0,
    "created_at": "2018-01-07T20:29:38Z",
    "updated_at": "2018-01-07T20:29:38Z",
    "sex": 0,
    "sequel": 2,
    "city_code": 0,
    "city_name": "",
    "product_companies": "",
    "ogp_image_url": "not_found",
    "ogp_description": "not_found"
  },
  {
    "id": 700,
    "title": "まめねこ",
    "title_short1": "まめねこ",
    "title_short2": "",
    "title_short3": "",
    "title_en": "",
    "public_url": "http://mameneko.club/",
    "twitter_account": "anime_mameneko",
    "twitter_hash_tag": "まめねこ",
    "cours_id": 0,
    "created_at": "2018-01-07T20:29:38Z",
    "updated_at": "2018-01-07T20:29:38Z",
    "sex": 0,
    "sequel": 2,
    "city_code": 0,
    "city_name": "",
    "product_companies": "",
    "ogp_image_url": "not_found",
    "ogp_description": "not_found"
  },
  {
    "id": 701,
    "title": "gdメン gdgd men's party",
    "title_short1": "gdメン",
    "title_short2": "",
    "title_short3": "",
    "title_en": "",
    "public_url": "http://gdmen.net/",
    "twitter_account": "gdmen2018",
    "twitter_hash_tag": "gdメン",
    "cours_id": 0,
    "created_at": "2018-01-07T20:29:38Z",
    "updated_at": "2018-01-07T20:29:38Z",
    "sex": 0,
    "sequel": 0,
    "city_code": 0,
    "city_name": "",
    "product_companies": "",
    "ogp_image_url": "not_found",
    "ogp_description": "not_found"
  },
  {
    "id": 702,
    "title": "弱虫ペダル GLORY LINE",
    "title_short1": "弱虫ペダル",
    "title_short2": "",
    "title_short3": "",
    "title_en": "",
    "public_url": "http://yowapeda.com/",
    "twitter_account": "yowapeda_anime",
    "twitter_hash_tag": "弱ペダ",
    "cours_id": 0,
    "created_at": "2018-01-07T20:29:38Z",
    "updated_at": "2018-01-07T20:29:38Z",
    "sex": 1,
    "sequel": 4,
    "city_code": 0,
    "city_name": "",
    "product_companies": "",
    "ogp_image_url": "not_found",
    "ogp_description": "not_found"
  },
  {
    "id": 703,
    "title": "怪獣娘～ウルトラ怪獣擬人化計画～ 第2期",
    "title_short1": "ウルトラ怪獣擬人化計画",
    "title_short2": "",
    "title_short3": "",
    "title_en": "",
    "public_url": "http://kaiju-gk.jp/anime/",
    "twitter_account": "ultrakaiju_gk",
    "twitter_hash_tag": "ウルトラ怪獣擬人化計画",
    "cours_id": 0,
    "created_at": "2018-01-07T20:29:38Z",
    "updated_at": "2018-01-07T20:29:38Z",
    "sex": 0,
    "sequel": 2,
    "city_code": 0,
    "city_name": "",
    "product_companies": "",
    "ogp_image_url": "not_found",
    "ogp_description": "not_found"
  },
  {
    "id": 704,
    "title": "オーバーロードⅡ",
    "title_short1": "オーバーロード",
    "title_short2": "",
    "title_short3": "",
    "title_en": "",
    "public_url": "http://overlord-anime.com/",
    "twitter_account": "over_lord_anime",
    "twitter_hash_tag": "overlord_anime",
    "cours_id": 0,
    "created_at": "2018-01-07T20:29:38Z",
    "updated_at": "2018-01-07T20:29:38Z",
    "sex": 0,
    "sequel": 2,
    "city_code": 0,
    "city_name": "",
    "product_companies": "",
    "ogp_image_url": "not_found",
    "ogp_description": "not_found"
  },
  {
    "id": 705,
    "title": "斉木楠雄のΨ難 第2期",
    "title_short1": "斉木楠雄のΨ難",
    "title_short2": "",
    "title_short3": "",
    "title_en": "",
    "public_url": "http://www.saikikusuo.com/",
    "twitter_account": "saikikusuo_PR",
    "twitter_hash_tag": "斉Ψ",
    "cours_id": 0,
    "created_at": "2018-01-07T20:29:38Z",
    "updated_at": "2018-01-07T20:29:38Z",
    "sex": 1,
    "sequel": 2,
    "city_code": 0,
    "city_name": "",
    "product_companies": "",
    "ogp_image_url": "not_found",
    "ogp_description": "not_found"
  },
  {
    "id": 706,
    "title": "ヴァイオレット・エヴァーガーデン",
    "title_short1": "ヴァイオレット・エヴァーガーデン",
    "title_short2": "",
    "title_short3": "",
    "title_en": "",
    "public_url": "http://violet-evergarden.jp/",
    "twitter_account": "Violet_Letter",
    "twitter_hash_tag": "VioletEvergarden",
    "cours_id": 0,
    "created_at": "2018-01-07T20:29:38Z",
    "updated_at": "2018-01-07T20:29:38Z",
    "sex": 0,
    "sequel": 0,
    "city_code": 0,
    "city_name": "",
    "product_companies": "",
    "ogp_image_url": "not_found",
    "ogp_description": "not_found"
  },
  {
    "id": 707,
    "title": "恋は雨上がりのように",
    "title_short1": "恋は雨上がりのように",
    "title_short2": "",
    "title_short3": "",
    "title_en": "",
    "public_url": "http://www.koiame-anime.com/",
    "twitter_account": "koiame_anime",
    "twitter_hash_tag": "恋雨",
    "cours_id": 0,
    "created_at": "2018-01-07T20:29:38Z",
    "updated_at": "2018-01-07T20:29:38Z",
    "sex": 0,
    "sequel": 0,
    "city_code": 0,
    "city_name": "",
    "product_companies": "",
    "ogp_image_url": "not_found",
    "ogp_description": "not_found"
  },
  {
    "id": 708,
    "title": "メルヘン・メドヘン",
    "title_short1": "メルヘン・メドヘン",
    "title_short2": "",
    "title_short3": "",
    "title_en": "",
    "public_url": "http://maerchen-anime.com/",
    "twitter_account": "maerchen_anime",
    "twitter_hash_tag": "メルヘンメドヘン",
    "cours_id": 0,
    "created_at": "2018-01-07T20:29:38Z",
    "updated_at": "2018-01-07T20:29:38Z",
    "sex": 0,
    "sequel": 0,
    "city_code": 0,
    "city_name": "",
    "product_companies": "",
    "ogp_image_url": "not_found",
    "ogp_description": "not_found"
  },
  {
    "id": 709,
    "title": "デスマーチからはじまる異世界狂想曲",
    "title_short1": "デスマーチからはじまる異世界狂想曲",
    "title_short2": "",
    "title_short3": "",
    "title_en": "",
    "public_url": "http://deathma-anime.com/",
    "twitter_account": "deathma_anime",
    "twitter_hash_tag": "デスマアニメ",
    "cours_id": 0,
    "created_at": "2018-01-07T20:29:38Z",
    "updated_at": "2018-01-07T20:29:38Z",
    "sex": 0,
    "sequel": 0,
    "city_code": 0,
    "city_name": "",
    "product_companies": "",
    "ogp_image_url": "not_found",
    "ogp_description": "not_found"
  },
  {
    "id": 710,
    "title": "ミイラの飼い方",
    "title_short1": "ミイラの飼い方",
    "title_short2": "",
    "title_short3": "",
    "title_en": "",
    "public_url": "http://www.tbs.co.jp/anime/miira/",
    "twitter_account": "miira_kaikata",
    "twitter_hash_tag": "ミイラの飼い方",
    "cours_id": 0,
    "created_at": "2018-01-07T20:29:38Z",
    "updated_at": "2018-01-07T20:29:38Z",
    "sex": 0,
    "sequel": 0,
    "city_code": 0,
    "city_name": "",
    "product_companies": "",
    "ogp_image_url": "not_found",
    "ogp_description": "not_found"
  },
  {
    "id": 711,
    "title": "だがしかし2",
    "title_short1": "だがしかし",
    "title_short2": "",
    "title_short3": "",
    "title_en": "",
    "public_url": "http://www.tbs.co.jp/anime/dagashi/",
    "twitter_account": "anime_dagashi",
    "twitter_hash_tag": "だがしかし",
    "cours_id": 0,
    "created_at": "2018-01-07T20:29:38Z",
    "updated_at": "2018-01-07T20:29:38Z",
    "sex": 0,
    "sequel": 2,
    "city_code": 0,
    "city_name": "",
    "product_companies": "",
    "ogp_image_url": "not_found",
    "ogp_description": "not_found"
  },
  {
    "id": 712,
    "title": "たくのみ。",
    "title_short1": "たくのみ",
    "title_short2": "",
    "title_short3": "",
    "title_en": "",
    "public_url": "http://www.tbs.co.jp/anime/takunomi/",
    "twitter_account": "anime_takunomi",
    "twitter_hash_tag": "たくのみ",
    "cours_id": 0,
    "created_at": "2018-01-07T20:29:38Z",
    "updated_at": "2018-01-07T20:29:38Z",
    "sex": 0,
    "sequel": 0,
    "city_code": 0,
    "city_name": "",
    "product_companies": "",
    "ogp_image_url": "not_found",
    "ogp_description": "not_found"
  },
  {
    "id": 713,
    "title": "ハクメイとミコチ",
    "title_short1": "ハクメイとミコチ",
    "title_short2": "",
    "title_short3": "",
    "title_en": "",
    "public_url": "http://hakumiko.com/",
    "twitter_account": "hakumikotv",
    "twitter_hash_tag": "hakumiko",
    "cours_id": 0,
    "created_at": "2018-01-07T20:29:38Z",
    "updated_at": "2018-01-07T20:29:38Z",
    "sex": 0,
    "sequel": 0,
    "city_code": 0,
    "city_name": "",
    "product_companies": "",
    "ogp_image_url": "not_found",
    "ogp_description": "not_found"
  },
  {
    "id": 714,
    "title": "覇弓 封神演義",
    "title_short1": "覇弓 封神演義",
    "title_short2": "",
    "title_short3": "",
    "title_en": "",
    "public_url": "http://tvhoushin-engi.com/",
    "twitter_account": "hoshinengi_tv",
    "twitter_hash_tag": "hoshinengi_tv",
    "cours_id": 0,
    "created_at": "2018-01-07T20:29:38Z",
    "updated_at": "2018-01-07T20:29:38Z",
    "sex": 0,
    "sequel": 0,
    "city_code": 0,
    "city_name": "",
    "product_companies": "",
    "ogp_image_url": "not_found",
    "ogp_description": "not_found"
  },
  {
    "id": 715,
    "title": "博多豚骨ラーメンズ",
    "title_short1": "博多豚骨ラーメンズ",
    "title_short2": "",
    "title_short3": "",
    "title_en": "",
    "public_url": "http://hakatatonkotsu-anime.com/",
    "twitter_account": "hakata_tonkotsu",
    "twitter_hash_tag": "博多豚骨",
    "cours_id": 0,
    "created_at": "2018-01-07T20:29:38Z",
    "updated_at": "2018-01-07T20:29:38Z",
    "sex": 0,
    "sequel": 0,
    "city_code": 0,
    "city_name": "",
    "product_companies": "",
    "ogp_image_url": "not_found",
    "ogp_description": "not_found"
  },
  {
    "id": 716,
    "title": "BEATLESS",
    "title_short1": "BEATLESS",
    "title_short2": "",
    "title_short3": "",
    "title_en": "",
    "public_url": "http://beatless-anime.jp/",
    "twitter_account": "BEATLESS_info",
    "twitter_hash_tag": "anime_beatless",
    "cours_id": 0,
    "created_at": "2018-01-07T20:29:38Z",
    "updated_at": "2018-01-07T20:29:38Z",
    "sex": 0,
    "sequel": 0,
    "city_code": 0,
    "city_name": "",
    "product_companies": "",
    "ogp_image_url": "not_found",
    "ogp_description": "not_found"
  },
  {
    "id": 717,
    "title": "キリングバイツ",
    "title_short1": "キリングバイツ",
    "title_short2": "",
    "title_short3": "",
    "title_en": "",
    "public_url": "http://killingbites-anime.com/",
    "twitter_account": "KB_anime",
    "twitter_hash_tag": "KB_anime",
    "cours_id": 0,
    "created_at": "2018-01-07T20:29:38Z",
    "updated_at": "2018-01-07T20:29:38Z",
    "sex": 0,
    "sequel": 0,
    "city_code": 0,
    "city_name": "",
    "product_companies": "",
    "ogp_image_url": "not_found",
    "ogp_description": "not_found"
  },
  {
    "id": 718,
    "title": "銀の墓守り(ガーディアン) 第2期",
    "title_short1": "銀の墓守り",
    "title_short2": "",
    "title_short3": "",
    "title_en": "",
    "public_url": "http://ginno-guardian.jp/",
    "twitter_account": "ginno_guardian",
    "twitter_hash_tag": "銀の墓守り",
    "cours_id": 0,
    "created_at": "2018-01-07T20:29:38Z",
    "updated_at": "2018-01-07T20:29:38Z",
    "sex": 0,
    "sequel": 2,
    "city_code": 0,
    "city_name": "",
    "product_companies": "",
    "ogp_image_url": "not_found",
    "ogp_description": "not_found"
  },
  {
    "id": 719,
    "title": "Fate／EXTRA Last Encore",
    "title_short1": "Fate/EXTRA Last Encore",
    "title_short2": "",
    "title_short3": "",
    "title_en": "",
    "public_url": "http://fate-extra-lastencore.com/",
    "twitter_account": "FateEXTRA_LE",
    "twitter_hash_tag": "FateEX_LE",
    "cours_id": 0,
    "created_at": "2018-01-07T20:29:38Z",
    "updated_at": "2018-01-07T20:29:38Z",
    "sex": 0,
    "sequel": 0,
    "city_code": 0,
    "city_name": "",
    "product_companies": "",
    "ogp_image_url": "not_found",
    "ogp_description": "not_found"
  }
]